nonebot_plugin_vv/__init__.py
nonebot_plugin_vv/utils.py
nonebot_plugin_vv-0.2.2.dist-info/licenses/LICENSE
nonebot_plugin_vv-0.2.2.dist-info/METADATA
nonebot_plugin_vv-0.2.2.dist-info/WHEEL
nonebot_plugin_vv-0.2.2.dist-info/top_level.txt
nonebot_plugin_vv-0.2.2.dist-info/RECORD
