Metadata-Version: 2.4
Name: nonebot-plugin-vv
Version: 0.2.2
Author-email: StillMisty <1772797842@qq.com>
License:                                  Apache License
Project-URL: Homepage, https://github.com/StillMisty/nonebot_plugin_vv
Classifier: Programming Language :: Python :: 3
Classifier: Programming Language :: Python :: 3.10
Classifier: Programming Language :: Python :: 3.11
Classifier: Programming Language :: Python :: 3.12
Classifier: Programming Language :: Python :: 3.13
Classifier: License :: OSI Approved :: Apache Software License
Classifier: Operating System :: OS Independent
Requires-Python: >=3.10
License-File: LICENSE
Requires-Dist: nonebot-adapter-onebot>=2.3
Requires-Dist: nonebot2>=2.3
Requires-Dist: nonebot_plugin_alconna>=0.53
Requires-Dist: httpx>=0.27.0
Dynamic: license-file
